Workbook

Sheet Risk Register
A1: ID | B1: Risk Description | C1: Pre-L (1–5) | D1: Pre-C (1–5) | E1: Pre-Score (L×C) | F1: Pre-Severity | G1: Mitigation (preventive) | H1: Contingency (reactive) | I1: Post-L (1–5) | J1: Post-C (1–5) | K1: Post-Score (L×C) | L1: Post-Severity
A2: TR-01 | B2: Capture mechanism fails to secure tumbling target (1 rpm about arbitrary axis) | C2: 4 | D2: 5 | E2: =C2*D2 -> 20 | F2: =IF(E2>=20,"Critical",IF(E2>=10,"High",IF(E2>=5,"Medium","Low"))) -> Critical | G2: Design capture mechanism with wide compliance (tolerant to ≥2 rpm, multi-axis tumble); perform Light Detection and Ranging (LIDAR) based motion characterisation prior to grappling. | H2: Abort capture sequence and retreat to safe hold point (>50 m); re-characterise target tumble; attempt secondary capture with adjusted alternative grappling settings; if repeated failure, mark target as non-recoverable and proceed to next. | I2: 2 | J2: 5 | K2: =I2*J2 -> 10 | L2: =IF(K2>=20,"Critical",IF(K2>=10,"High",IF(K2>=5,"Medium","Low"))) -> High
A3: TR-02 | B3: Debris generation during disassembly (fragments > 1 cm released into GEO belt) - Recycling Hub | C3: 3 | D3: 5 | E3: =C3*D3 -> 15 | F3: =IF(E3>=20,"Critical",IF(E3>=10,"High",IF(E3>=5,"Medium","Low"))) -> High | G3: Use low-energy cutting tools within an enclosed capture cage to contain any loose pieces; design and test the disassembly process to minimise fragment release. | H3: Stop disassembly immediately on debris detection; deploy debris-containment net (capture fragments); use onboard cameras to track fragments. | I3: 2 | J3: 4 | K3: =I3*J3 -> 8 | L3: =IF(K3>=20,"Critical",IF(K3>=10,"High",IF(K3>=5,"Medium","Low"))) -> Medium
A4: TR-03 | B4: Autonomous Failure Management (AFM) failure during close-proximity operations (range < 100 m) leads to a collision with the target | C4: 3 | D4: 5 | E4: =C4*D4 -> 15 | F4: =IF(E4>=20,"Critical",IF(E4>=10,"High",IF(E4>=5,"Medium","Low"))) -> High | G4: Implement triple-redundant AFM with independent sensor chains (LIDAR, camera); extensive simulation of failure modes. | H4: Trigger autonomous collision-avoidance manoeuvre (CAM) to retreat to safe distance; switch to backup AFM; resume only after ground confirmation; if both backups fail, abort to manoeuvre. | I4: 2 | J4: 5 | K4: =I4*J4 -> 10 | L4: =IF(K4>=20,"Critical",IF(K4>=10,"High",IF(K4>=5,"Medium","Low"))) -> High
A5: TR-04 | B5: Propellant depletion before completion of all 5 capture missions | C5: 3 | D5: 4 | E5: =C5*D5 -> 12 | F5: =IF(E5>=20,"Critical",IF(E5>=10,"High",IF(E5>=5,"Medium","Low"))) -> High | G5: Conservative ΔV budget with ≥20 % margin; optimised mission sequencing to minimise transfers; high-Isp electric propulsion for orbit raising. | H5: Reprioritise remaining captures based on value/proximity; skip lowest-priority target(s). | I5: 2 | J5: 4 | K5: =I5*J5 -> 8 | L5: =IF(K5>=20,"Critical",IF(K5>=10,"High",IF(K5>=5,"Medium","Low"))) -> Medium
A6: TR-05 | B6: Navigation sensor failure during final approach (range < 10 m) causes position error exceeding 1 m | C6: 3 | D6: 4 | E6: =C6*D6 -> 12 | F6: =IF(E6>=20,"Critical",IF(E6>=10,"High",IF(E6>=5,"Medium","Low"))) -> High | G6: Redundant navigation architecture (LIDAR + stereo cameras + flash imager) with cross-checking; calibrate sensors pre-approach; define abort triggers on position error >0.3 m. | H6: Hold position and switch to backup sensor chain; if error persists, retreat to 100 m, recalibrate, and re-approach; escalate to ground for teleoperated final approach if available. | I6: 2 | J6: 4 | K6: =I6*J6 -> 8 | L6: =IF(K6>=20,"Critical",IF(K6>=10,"High",IF(K6>=5,"Medium","Low"))) -> Medium
A7: TR-06 | B7: Thermal control failure causes electronics or propellants to exceed operational temperature range | C7: 2 | D7: 4 | E7: =C7*D7 -> 8 | F7: =IF(E7>=20,"Critical",IF(E7>=10,"High",IF(E7>=5,"Medium","Low"))) -> Medium | G7: Active thermal control with redundant heaters/radiators; Multi-Layer Insulation (MLI) on critical components; thermal model validated by Thermal Vacuum (TVAC) testing; temperature margins ≥10 °C against operational limits. | H7: Enter thermal safe mode: reorient spacecraft to balance solar input, dispose of non-critical loads, activate survival heaters; resume operations after temperatures stabilise within limits. | I7: 1 | J7: 4 | K7: =I7*J7 -> 4 | L7: =IF(K7>=20,"Critical",IF(K7>=10,"High",IF(K7>=5,"Medium","Low"))) -> Low
A8: TR-07 | B8: Propulsion failure during critical phase: Loss of the main propulsion system during approach. | C8: 2 | D8: 5 | E8: =C8*D8 -> 10 | F8: =IF(E8>=20,"Critical",IF(E8>=10,"High",IF(E8>=5,"Medium","Low"))) -> High | G8: Dual-propulsion (main) system with isolatable branches; pre-burn tests; conservative duty cycles; redundant thrusters. | H8: Switch to backup propulsion system; if unavailable, use (Reaction Control System) RCS for safe retreat manoeuvre; place spacecraft in stable hold orbit and assess recovery options from ground. | I8: 1 | J8: 5 | K8: =I8*J8 -> 5 | L8: =IF(K8>=20,"Critical",IF(K8>=10,"High",IF(K8>=5,"Medium","Low"))) -> Medium
A9: TR-08 | B9: EOL spacecraft remains in GEO protected zone (35,586–35,986 km) after mission end instead of being transferred to the Recycling Hub | C9: 2 | D9: 5 | E9: =C9*D9 -> 10 | F9: =IF(E9>=20,"Critical",IF(E9>=10,"High",IF(E9>=5,"Medium","Low"))) -> High | G9: Reserve dedicated end-of-life ΔV to transfer the spacecraft to the Recycling Hub at mission end; maintain hub rendezvous capability throughout mission life. | H9: If primary EOL transfer burn fails, execute transfer using residual Reaction Control System (RCS) propellant in multiple smaller burns; if still unable to reach the hub, raise orbit to graveyard zone (≥300 km above GEO) and notify regulators. | I9: 1 | J9: 5 | K9: =I9*J9 -> 5 | L9: =IF(K9>=20,"Critical",IF(K9>=10,"High",IF(K9>=5,"Medium","Low"))) -> Medium
A10: TR-09 | B10: Micrometeoroid or orbital debris impact penetrates propulsion in GEO graveyard environment | C10: 2 | D10: 4 | E10: =C10*D10 -> 8 | F10: =IF(E10>=20,"Critical",IF(E10>=10,"High",IF(E10>=5,"Medium","Low"))) -> Medium | G10: Shielding (MLI) over propellant tanks; redundant tank isolation valves; orbit selection minimising debris exposure; periodic leak detection via pressure sensors. | H10: Isolate affected propellant branch via valves; switch to redundant tank; reduce remaining mission scope to match available propellant; escalate to graveyard disposal if leak uncontained. | I10: 1 | J10: 4 | K10: =I10*J10 -> 4 | L10: =IF(K10>=20,"Critical",IF(K10>=10,"High",IF(K10>=5,"Medium","Low"))) -> Low
A11: TR-10 | B11: Communication blackout during a critical autonomous sequence causes loss of ground override capability | C11: 3 | D11: 3 | E11: =C11*D11 -> 9 | F11: =IF(E11>=20,"Critical",IF(E11>=10,"High",IF(E11>=5,"Medium","Low"))) -> Medium | G11: Pre-loaded autonomous safe-state behaviour for any comm loss >X minutes; redundant Telemetry, Tracking & Command (TT&C) systems (S-band + backup); use of multiple ground stations and relay satellites during critical ops. | H11: Spacecraft autonomously enters safe hold and aborts active sequence; ground re-establishes link via secondary station/antenna; resume operations only after full check and state verification. | I11: 2 | J11: 3 | K11: =I11*J11 -> 6 | L11: =IF(K11>=20,"Critical",IF(K11>=10,"High",IF(K11>=5,"Medium","Low"))) -> Medium
A12: TR-11 | B12: Solar panel damage during contact with tumbling target reduces power by > 50% | C12: 3 | D12: 4 | E12: =C12*D12 -> 12 | F12: =IF(E12>=20,"Critical",IF(E12>=10,"High",IF(E12>=5,"Medium","Low"))) -> High | G12: Foldable solar arrays retracted during contact phases; protective shielding over cells facing target; capture geometry analysis to keep arrays clear of contact zones. | H12: Reconfigure power management: dispose of non-essential loads, throttle electric propulsion, prioritise survival systems; reorient remaining array area for max insolation (amount of sunlight hitting the solar panels); adjust mission scope to match available power. | I12: 2 | J12: 4 | K12: =I12*J12 -> 8 | L12: =IF(K12>=20,"Critical",IF(K12>=10,"High",IF(K12>=5,"Medium","Low"))) -> Medium
A13: TR-12 | B13: Target spacecraft misidentified prior to capture, causing a failed grapple or structural overload | C13: 3 | D13: 4 | E13: =C13*D13 -> 12 | F13: =IF(E13>=20,"Critical",IF(E13>=10,"High",IF(E13>=5,"Medium","Low"))) -> High | G13: Pre-mission target catalogue verification using ground radar/optical and onboard imagery; ID confirmation via multiple features (shape, radio signal) before committing to capture; ground approval required. | H13: Abort capture before mechanical contact; retreat to safe distance (>100 m); re-image and re-identify target; if confirmed wrong, abandon engagement and proceed to next valid target. | I13: 2 | J13: 4 | K13: =I13*J13 -> 8 | L13: =IF(K13>=20,"Critical",IF(K13>=10,"High",IF(K13>=5,"Medium","Low"))) -> Medium
... A31: TR-30 | B31: Ground mission operations centre failure causes extended loss of spacecraft commanding and telemetry monitoring during an active operational phase | C31: 2 | D31: 4 | E31: =C31*D31 -> 8 | F31: =IF(E31>=20,"Critical",IF(E31>=10,"High",IF(E31>=5,"Medium","Low"))) -> Medium | G31: Geographically redundant primary and backup Mission Operations Centre (MOC); rehearsed handover procedures; spacecraft autonomy sized to operate ≥48 h without ground contact. | H31: Spacecraft continues on stored timeline or enters safe-hold past autonomy window; activate backup MOC; resume nominal commanding once link and operations are restored. | I31: 1 | J31: 4 | K31: =I31*J31 -> 4 | L31: =IF(K31>=20,"Critical",IF(K31>=10,"High",IF(K31>=5,"Medium","Low"))) -> Low
B34: Legend: | C34: Low (1–4) | D34: Medium (5–9) | E34: High (10–16) | F34: Critical (20–25)

Sheet Risk Summary
A1: ID | B1: Risk Description | C1: Pre-L (1–5) | D1: Pre-C (1–5) | E1: Pre-Score (L×C) | F1: Pre-Severity | G1: Post-L (1–5) | H1: Post-C (1–5) | I1: Post-Score (L×C) | J1: Post-Severity
A2: ='Risk Register'!A2 -> TR-01 | B2: ='Risk Register'!B2 -> Capture mechanism fails to secure tumbling target (1 rpm about arbitrary axis) | C2: ='Risk Register'!C2 -> 4 | D2: ='Risk Register'!D2 -> 5 | E2: ='Risk Register'!E2 -> 20 | F2: ='Risk Register'!F2 -> Critical | I2: =IF(AND(G2<>"",H2<>""),G2*H2,"") | J2: =IF(I2="","",IF(I2>=20,"Critical",IF(I2>=10,"High",IF(I2>=5,"Medium","Low"))))
A3: ='Risk Register'!A3 -> TR-02 | B3: ='Risk Register'!B3 -> Debris generation during disassembly (fragments > 1 cm released into GEO belt) - Recycling Hub | C3: ='Risk Register'!C3 -> 3 | D3: ='Risk Register'!D3 -> 5 | E3: ='Risk Register'!E3 -> 15 | F3: ='Risk Register'!F3 -> High | I3: =IF(AND(G3<>"",H3<>""),G3*H3,"") | J3: =IF(I3="","",IF(I3>=20,"Critical",IF(I3>=10,"High",IF(I3>=5,"Medium","Low"))))
A4: ='Risk Register'!A4 -> TR-03 | B4: ='Risk Register'!B4 -> Autonomous Failure Management (AFM) failure during close-proximity operations (range < 100 m) leads to a collision with the target | C4: ='Risk Register'!C4 -> 3 | D4: ='Risk Register'!D4 -> 5 | E4: ='Risk Register'!E4 -> 15 | F4: ='Risk Register'!F4 -> High | I4: =IF(AND(G4<>"",H4<>""),G4*H4,"") | J4: =IF(I4="","",IF(I4>=20,"Critical",IF(I4>=10,"High",IF(I4>=5,"Medium","Low"))))
A5: ='Risk Register'!A5 -> TR-04 | B5: ='Risk Register'!B5 -> Propellant depletion before completion of all 5 capture missions | C5: ='Risk Register'!C5 -> 3 | D5: ='Risk Register'!D5 -> 4 | E5: ='Risk Register'!E5 -> 12 | F5: ='Risk Register'!F5 -> High | I5: =IF(AND(G5<>"",H5<>""),G5*H5,"") | J5: =IF(I5="","",IF(I5>=20,"Critical",IF(I5>=10,"High",IF(I5>=5,"Medium","Low"))))
A6: ='Risk Register'!A6 -> TR-05 | B6: ='Risk Register'!B6 -> Navigation sensor failure during final approach (range < 10 m) causes position error exceeding 1 m | C6: ='Risk Register'!C6 -> 3 | D6: ='Risk Register'!D6 -> 4 | E6: ='Risk Register'!E6 -> 12 | F6: ='Risk Register'!F6 -> High | I6: =IF(AND(G6<>"",H6<>""),G6*H6,"") | J6: =IF(I6="","",IF(I6>=20,"Critical",IF(I6>=10,"High",IF(I6>=5,"Medium","Low"))))
A7: ='Risk Register'!A7 -> TR-06 | B7: ='Risk Register'!B7 -> Thermal control failure causes electronics or propellants to exceed operational temperature range | C7: ='Risk Register'!C7 -> 2 | D7: ='Risk Register'!D7 -> 4 | E7: ='Risk Register'!E7 -> 8 | F7: ='Risk Register'!F7 -> Medium | I7: =IF(AND(G7<>"",H7<>""),G7*H7,"") | J7: =IF(I7="","",IF(I7>=20,"Critical",IF(I7>=10,"High",IF(I7>=5,"Medium","Low"))))
A8: ='Risk Register'!A8 -> TR-07 | B8: ='Risk Register'!B8 -> Propulsion failure during critical phase: Loss of the main propulsion system during approach. | C8: ='Risk Register'!C8 -> 2 | D8: ='Risk Register'!D8 -> 5 | E8: ='Risk Register'!E8 -> 10 | F8: ='Risk Register'!F8 -> High | I8: =IF(AND(G8<>"",H8<>""),G8*H8,"") | J8: =IF(I8="","",IF(I8>=20,"Critical",IF(I8>=10,"High",IF(I8>=5,"Medium","Low"))))
A9: ='Risk Register'!A9 -> TR-08 | B9: ='Risk Register'!B9 -> EOL spacecraft remains in GEO protected zone (35,586–35,986 km) after mission end instead of being transferred to the Recycling Hub | C9: ='Risk Register'!C9 -> 2 | D9: ='Risk Register'!D9 -> 5 | E9: ='Risk Register'!E9 -> 10 | F9: ='Risk Register'!F9 -> High | I9: =IF(AND(G9<>"",H9<>""),G9*H9,"") | J9: =IF(I9="","",IF(I9>=20,"Critical",IF(I9>=10,"High",IF(I9>=5,"Medium","Low"))))
A10: ='Risk Register'!A10 -> TR-09 | B10: ='Risk Register'!B10 -> Micrometeoroid or orbital debris impact penetrates propulsion in GEO graveyard environment | C10: ='Risk Register'!C10 -> 2 | D10: ='Risk Register'!D10 -> 4 | E10: ='Risk Register'!E10 -> 8 | F10: ='Risk Register'!F10 -> Medium | I10: =IF(AND(G10<>"",H10<>""),G10*H10,"") | J10: =IF(I10="","",IF(I10>=20,"Critical",IF(I10>=10,"High",IF(I10>=5,"Medium","Low"))))
A11: ='Risk Register'!A11 -> TR-10 | B11: ='Risk Register'!B11 -> Communication blackout during a critical autonomous sequence causes loss of ground override capability | C11: ='Risk Register'!C11 -> 3 | D11: ='Risk Register'!D11 -> 3 | E11: ='Risk Register'!E11 -> 9 | F11: ='Risk Register'!F11 -> Medium | I11: =IF(AND(G11<>"",H11<>""),G11*H11,"") | J11: =IF(I11="","",IF(I11>=20,"Critical",IF(I11>=10,"High",IF(I11>=5,"Medium","Low"))))
A12: ='Risk Register'!A12 -> TR-11 | B12: ='Risk Register'!B12 -> Solar panel damage during contact with tumbling target reduces power by > 50% | C12: ='Risk Register'!C12 -> 3 | D12: ='Risk Register'!D12 -> 4 | E12: ='Risk Register'!E12 -> 12 | F12: ='Risk Register'!F12 -> High | I12: =IF(AND(G12<>"",H12<>""),G12*H12,"") | J12: =IF(I12="","",IF(I12>=20,"Critical",IF(I12>=10,"High",IF(I12>=5,"Medium","Low"))))
A13: ='Risk Register'!A13 -> TR-12 | B13: ='Risk Register'!B13 -> Target spacecraft misidentified prior to capture, causing a failed grapple or structural overload | C13: ='Risk Register'!C13 -> 3 | D13: ='Risk Register'!D13 -> 4 | E13: ='Risk Register'!E13 -> 12 | F13: ='Risk Register'!F13 -> High | I13: =IF(AND(G13<>"",H13<>""),G13*H13,"") | J13: =IF(I13="","",IF(I13>=20,"Critical",IF(I13>=10,"High",IF(I13>=5,"Medium","Low"))))
... A31: ='Risk Register'!A31 -> TR-30 | B31: ='Risk Register'!B31 -> Ground mission operations centre failure causes extended loss of spacecraft commanding and telemetry monitoring during an active operational phase | C31: ='Risk Register'!C31 -> 2 | D31: ='Risk Register'!D31 -> 4 | E31: ='Risk Register'!E31 -> 8 | F31: ='Risk Register'!F31 -> Medium | I31: =IF(AND(G31<>"",H31<>""),G31*H31,"") | J31: =IF(I31="","",IF(I31>=20,"Critical",IF(I31>=10,"High",IF(I31>=5,"Medium","Low"))))

Sheet Pre-Mitigation Map
A1: Pre-Mitigation Risk Map — REAVER DSE
A2: L \ C | B2: C1 | C2: C2 | D2: C3 | E2: C4 | F2: C5
A3: L5 | D3: R-04
A4: L4 | E4: R-01 R-02
A5: L3 | D5: R-05 R-09 | E5: R-03 R-06 R-10 | F5: R-07
A6: L2 | E6: R-08
A7: L1
B9: ← Consequence (C) →
A11: Legend: | B11: Low (1–4) | C11: Medium (5–9) | D11: High (10–16) | E11: Critical (20–25)

Sheet Post-Mitigation Map
A1: Post-Mitigation Risk Map — REAVER DSE
A2: L \ C | B2: C1 | C2: C2 | D2: C3 | E2: C4 | F2: C5
A3: L5
A4: L4
A5: L3 | D5: R-04
A6: L2 | D6: R-01 R-02 R-05 R-08 R-09 | E6: R-03 R-06 R-10 | F6: R-07
A7: L1
B9: ← Consequence (C) →
A11: Legend: | B11: Low (1–4) | C11: Medium (5–9) | D11: High (10–16) | E11: Critical (20–25)
